kypo_aws_commons/__init__.py
kypo_aws_commons/security_groups/__init__.py
kypo_aws_commons/security_groups/construct.py
kypo_aws_commons/security_groups/model.py
kypo_aws_commons-0.1.1.dist-info/METADATA
kypo_aws_commons-0.1.1.dist-info/WHEEL
kypo_aws_commons-0.1.1.dist-info/RECORD
