Metadata-Version: 2.1
Name: kypo-aws-commons
Version: 0.1.1
Summary: 
Author: Juraj Paluba
Author-email: 492988@mail.muni.cz
Requires-Python: >=3.10,<4.0
Classifier: Programming Language :: Python :: 3
Classifier: Programming Language :: Python :: 3.10
Classifier: Programming Language :: Python :: 3.11
Classifier: Programming Language :: Python :: 3.12
Requires-Dist: cdktf (>=0.20.3,<0.21.0)
Requires-Dist: cdktf-cdktf-provider-aws (>=19.5.0,<20.0.0)
Requires-Dist: yamlize (>=0.7.1,<0.8.0)
